cadCAD_tools/__init__.py
cadCAD_tools/preparation.py
cadCAD_tools/types.py
cadCAD_tools/utils.py
cadCAD_tools/execution/__init__.py
cadCAD_tools/execution/easy_run.py
cadCAD_tools/profiling/__init__.py
cadCAD_tools/profiling/profile_run.py
cadCAD_tools/profiling/visualizations.py
cadCAD_tools-0.0.1.5.dist-info/LICENSE
cadCAD_tools-0.0.1.5.dist-info/METADATA
cadCAD_tools-0.0.1.5.dist-info/WHEEL
cadCAD_tools-0.0.1.5.dist-info/top_level.txt
cadCAD_tools-0.0.1.5.dist-info/RECORD
