Metadata-Version: 2.1
Name: cadCAD-tools
Version: 0.0.1.5
Summary: tools
Home-page: https://github.com/cadCAD-org/cadCAD-tools
Author: Danilo Lessa Bernardineli
Author-email: danilo@block.science, danilo.lessa@gmail.com
License: UNKNOWN
Platform: UNKNOWN
License-File: LICENSE
Requires-Dist: cadCAD
Requires-Dist: pandas
Requires-Dist: tqdm
Requires-Dist: numpy
Requires-Dist: plotly
